{"client":"Thunder Client","collectionName":"PROJETO02_M03_ROTA_CIDADES","dateExported":"2021-11-09T23:15:02.993Z","version":"1.1","folders":[],"requests":[{"containerId":"","sortNum":10000,"headers":[{"name":"Accept","value":"*/*"},{"name":"User-Agent","value":"Thunder Client (https://www.thunderclient.io)"}],"colId":"7edccc23-bbd6-45cb-88d1-c55847976e53","name":"ROTA GERAL CIDADES","url":"https://projeto2-m3.herokuapp.com/cidades/","method":"GET","modified":"2021-11-09T22:29:06.429Z","created":"2021-11-09T22:27:50.762Z","_id":"00ee4351-2a6f-4f2d-a797-e83096f69f53","params":[],"tests":[]},{"containerId":"","sortNum":20000,"headers":[{"name":"Accept","value":"*/*"},{"name":"User-Agent","value":"Thunder Client (https://www.thunderclient.io)"}],"colId":"7edccc23-bbd6-45cb-88d1-c55847976e53","name":"ADICIONANDO NOVO ITEM NA ROTA CIDADES","url":"https://projeto2-m3.herokuapp.com/cidades/add/","method":"POST","modified":"2021-11-09T22:50:54.318Z","created":"2021-11-09T22:29:50.117Z","_id":"7085c084-fb5c-4955-a861-967c572f697c","params":[],"body":{"type":"json","raw":"{\r\n\"nome\":\"Rio de Janeiro\",\r\n\"qtdDeBairros\":196,\r\n\"populacao\":6775561,\r\n\"aniversarioCidade\":\"1565-03-01\"\r\n}","form":[]},"tests":[]},{"containerId":"","sortNum":30000,"headers":[{"name":"Accept","value":"*/*"},{"name":"User-Agent","value":"Thunder Client (https://www.thunderclient.io)"}],"colId":"7edccc23-bbd6-45cb-88d1-c55847976e53","name":"LISTANDO TODAS CIDADES","url":"https://projeto2-m3.herokuapp.com/cidades/listall/","method":"GET","modified":"2021-11-09T22:51:59.648Z","created":"2021-11-09T22:51:43.604Z","_id":"4802bf41-3e40-41b8-8428-90559c80da3a","params":[],"tests":[]},{"containerId":"","sortNum":40000,"headers":[{"name":"Accept","value":"*/*"},{"name":"User-Agent","value":"Thunder Client (https://www.thunderclient.io)"}],"colId":"7edccc23-bbd6-45cb-88d1-c55847976e53","name":"LISTANDO UMA CIDADE POR NOME","url":"https://projeto2-m3.herokuapp.com/cidades/listname/Campinas","method":"GET","modified":"2021-11-09T22:53:27.749Z","created":"2021-11-09T22:53:22.735Z","_id":"e0debb54-53b7-4adf-82c6-13a902809816","params":[],"tests":[]},{"containerId":"","sortNum":50000,"headers":[{"name":"Accept","value":"*/*"},{"name":"User-Agent","value":"Thunder Client (https://www.thunderclient.io)"}],"colId":"7edccc23-bbd6-45cb-88d1-c55847976e53","name":"ALTERANDO UMA CIDADE","url":"https://projeto2-m3.herokuapp.com/cidades/update/618afb5089c70628b0fe8154","method":"PUT","modified":"2021-11-09T22:56:13.556Z","created":"2021-11-09T22:54:27.750Z","_id":"b73ed6a9-f485-48a2-a717-684c15ce40b8","params":[],"body":{"type":"json","raw":"{\r\n\"nome\":\"Rio de Janeiro\",\r\n\"qtdDeBairros\":196,\r\n\"populacao\":6775561,\r\n\"aniversarioCidade\":\"1565-03-01\"\r\n}","form":[]},"tests":[]},{"containerId":"","sortNum":60000,"headers":[{"name":"Accept","value":"*/*"},{"name":"User-Agent","value":"Thunder Client (https://www.thunderclient.io)"}],"colId":"7edccc23-bbd6-45cb-88d1-c55847976e53","name":"DELETANDO UMA CIDADE","url":"https://projeto2-m3.herokuapp.com/cidades/delete/618afb5089c70628b0fe8154","method":"DELETE","modified":"2021-11-09T23:00:05.564Z","created":"2021-11-09T22:56:55.471Z","_id":"0bf18187-1014-4757-9c10-36680a6b8a41","params":[],"tests":[]}]}
